<?xml version="1.0" encoding="utf-8" ?>
<dwsync>
<file name="album-af.jpg" server="ftp.idscrm.com" local="131492879100569424" remote="131949306600000000" />
<file name="arrow_next.gif" server="ftp.idscrm.com" local="131492879095773856" remote="131949306600000000" />
<file name="arrow_prev.gif" server="ftp.idscrm.com" local="131492879096087691" remote="131949306600000000" />
<file name="button_close.gif" server="ftp.idscrm.com" local="131492879092086374" remote="131949306600000000" />
<file name="button_logout.gif" server="ftp.idscrm.com" local="131492879092507606" remote="131949306600000000" />
<file name="Buyers-and-Sellers.jpg" server="ftp.idscrm.com" local="131492879109574118" remote="131949306600000000" />
<file name="content_bg.gif" server="ftp.idscrm.com" local="131492879088248460" remote="131949306600000000" />
<file name="create-recurring-invoice.php" server="ftp.idscrm.com" local="131949302291448496" remote="131949306600000000" />
<file name="dropdown.gif" server="ftp.idscrm.com" local="131492879083758751" remote="131949306600000000" />
<file name="dropup.gif" server="ftp.idscrm.com" local="131492879082031693" remote="131949306600000000" />
<file name="email.gif" server="ftp.idscrm.com" local="131492879079910037" remote="131949306600000000" />
<file name="error_log" server="ftp.idscrm.com" local="131492879075065710" remote="131949306600000000" />
<file name="first-time-real-estate-buyers.jpg" server="ftp.idscrm.com" local="131492879078722773" remote="131949306600000000" />
<file name="footer_bg.gif" server="ftp.idscrm.com" local="131492879070221769" remote="131949306600000000" />
<file name="gradient37.gif" server="ftp.idscrm.com" local="131492879067062752" remote="131949306600000000" />
<file name="gradient47.gif" server="ftp.idscrm.com" local="131492879065373975" remote="131949306600000000" />
<file name="gradient67.gif" server="ftp.idscrm.com" local="131492879062529953" remote="131949306600000000" />
<file name="header_bg.gif" server="ftp.idscrm.com" local="131492879061346860" remote="131949306600000000" />
<file name="homeownership.JPG" server="ftp.idscrm.com" local="131492879058740802" remote="131949306600000000" />
<file name="icon_c01.gif" server="ftp.idscrm.com" local="131492879057677667" remote="131949306600000000" />
<file name="icon_c02.gif" server="ftp.idscrm.com" local="131492879053893492" remote="131949306600000000" />
<file name="icon_c03.gif" server="ftp.idscrm.com" local="131492879053067890" remote="131949306600000000" />
<file name="icon_c04.gif" server="ftp.idscrm.com" local="131492879050537069" remote="131949306600000000" />
<file name="icon_c05.gif" server="ftp.idscrm.com" local="131492879048727128" remote="131949306600000000" />
<file name="icon_c06.gif" server="ftp.idscrm.com" local="131492879047040218" remote="131949306600000000" />
<file name="icon_c07.gif" server="ftp.idscrm.com" local="131492879044753470" remote="131949306600000000" />
<file name="icon_c08.gif" server="ftp.idscrm.com" local="131492879043264020" remote="131949306600000000" />
<file name="icon_c09.gif" server="ftp.idscrm.com" local="131492879040720706" remote="131949306600000000" />
<file name="icon_c10.gif" server="ftp.idscrm.com" local="131492879038879701" remote="131949306600000000" />
<file name="icon_c11.gif" server="ftp.idscrm.com" local="131492879036718286" remote="131949306600000000" />
<file name="icon_c41.gif" server="ftp.idscrm.com" local="131492879034537542" remote="131949306600000000" />
<file name="icon_c42.gif" server="ftp.idscrm.com" local="131492879032979157" remote="131949306600000000" />
<file name="icon_c43.gif" server="ftp.idscrm.com" local="131492879030495631" remote="131949306600000000" />
<file name="icon_c61.gif" server="ftp.idscrm.com" local="131492879028311197" remote="131949306600000000" />
<file name="icon_c62.gif" server="ftp.idscrm.com" local="131492879026181848" remote="131949306600000000" />
<file name="icon_c63.gif" server="ftp.idscrm.com" local="131492879022702674" remote="131949306600000000" />
<file name="icon_comp.gif" server="ftp.idscrm.com" local="131492879024346191" remote="131949306600000000" />
<file name="icon_f1.gif" server="ftp.idscrm.com" local="131492879018698313" remote="131949306600000000" />
<file name="icon_h1.gif" server="ftp.idscrm.com" local="131492879017167972" remote="131949306600000000" />
<file name="icon_h2.gif" server="ftp.idscrm.com" local="131492879014692402" remote="131949306600000000" />
<file name="icon_h3.gif" server="ftp.idscrm.com" local="131492879013384043" remote="131949306600000000" />
<file name="icon_l1.gif" server="ftp.idscrm.com" local="131492879010840182" remote="131949306600000000" />
<file name="icon_l2.gif" server="ftp.idscrm.com" local="131492879009310179" remote="131949306600000000" />
<file name="idscrm-logo.jpg" server="ftp.idscrm.com" local="131492879006834766" remote="131949306600000000" />
<file name="Invest-in-Real-Estate.jpg" server="ftp.idscrm.com" local="131492879100776053" remote="131949306600000000" />
<file name="jqm-sitebg.png" server="ftp.idscrm.com" local="131492879005304148" remote="131949306600000000" />
<file name="jquery-mobile-logo.png" server="ftp.idscrm.com" local="131492879002855537" remote="131949306600000000" />
<file name="linehr.gif" server="ftp.idscrm.com" local="131492879001300190" remote="131949306600000000" />
<file name="logo.jpg" server="ftp.idscrm.com" local="131492878998457837" remote="131949306600000000" />
<file name="logo.png" server="ftp.idscrm.com" local="131492878997627388" remote="131949306600000000" />
<file name="logo_footer.jpg" server="ftp.idscrm.com" local="131492878994448772" remote="131949306600000000" />
<file name="pimpa_no.gif" server="ftp.idscrm.com" local="131492878993664577" remote="131949306600000000" />
<file name="pimpa_yes.gif" server="ftp.idscrm.com" local="131492878989021391" remote="131949306600000000" />
<file name="real-estate-flipping.jpg" server="ftp.idscrm.com" local="131492878989556092" remote="131949306600000000" />
<file name="red-xarrow.gif" server="ftp.idscrm.com" local="131492878985439268" remote="131949306600000000" />
<file name="slide1.jpg" server="ftp.idscrm.com" local="131492878982129741" remote="131949306600000000" />
<file name="slide2.jpg" server="ftp.idscrm.com" local="131492878981552339" remote="131949306600000000" />
<file name="slide3.jpg" server="ftp.idscrm.com" local="131492878977284298" remote="131949306600000000" />
<file name="spacer.gif" server="ftp.idscrm.com" local="131492878976602834" remote="131949306600000000" />
<file name="tab_icon1.gif" server="ftp.idscrm.com" local="131492878973003324" remote="131949306600000000" />
<file name="tab_icon2.gif" server="ftp.idscrm.com" local="131492878973003324" remote="131949306600000000" />
<file name="tab_icon3.gif" server="ftp.idscrm.com" local="131492878968865805" remote="131949306600000000" />
<file name="tab_icon3.png" server="ftp.idscrm.com" local="131492878965368776" remote="131949306600000000" />
<file name="version.png" server="ftp.idscrm.com" local="131492878967652415" remote="131949306600000000" />
</dwsync>